lychpy-0.0.2.dist-info/METADATA
lychpy-0.0.2.dist-info/WHEEL
lychpy-0.0.2.dist-info/license_files/LICENSE
lychpy.libs/libkeyutils-dfe70bd6.so.1
lychpy.libs/libk5crypto-b1f99d5c.so.3
lychpy.libs/libpcre-9513aab5.so.1
lychpy.libs/libcom_err-2abe824b.so.2
lychpy.libs/libselinux-0922c95c.so.1
lychpy.libs/libcrypto-d3570994.so.10
lychpy.libs/libssl-cd1d6220.so.10
lychpy.libs/libkrb5support-d0bcff84.so.0
lychpy.libs/libkrb5-fcafa220.so.3
lychpy.libs/libgssapi_krb5-497db0c6.so.2
lychpy/__init__.py
lychpy/lychpy.cpython-37m-x86_64-linux-gnu.so
lychpy-0.0.2.dist-info/RECORD
